cv4t/__init__.py
cv4t/color.py
cv4t/dnn.py
cv4t/draw_lib.py
cv4t/face_detection.py
cv4t/hand_and_gesture.py
cv4t/mask_align.py
cv4t/pose_detection.py
cv4t/try_pil_draw_text.py
cv4t/try_png_overlay.py
cv4t/model_needed/hand_gesture_recognizer.task
視覺模組/__init__.py
cv4t-0.1.0.dist-info/LICENSE
cv4t-0.1.0.dist-info/METADATA
cv4t-0.1.0.dist-info/WHEEL
cv4t-0.1.0.dist-info/top_level.txt
cv4t-0.1.0.dist-info/RECORD
