Metadata-Version: 2.1
Name: cv4t
Version: 0.1.0
Summary: Computer Vision wrapper library for Teenagers
Home-page: https://github.com/beardad1975/cv4t
Author: Wen-Hung, Chang 張文宏
Author-email: beardad1975@nmes.tyc.edu.tw
Platform: Windows
Classifier: Programming Language :: Python :: 3
Classifier: License :: OSI Approved :: MIT License
Classifier: Operating System :: Microsoft :: Windows
Classifier: Natural Language :: Chinese (Traditional)
Requires-Python: >=3.8
License-File: LICENSE
Requires-Dist: opencv-contrib-python (>=4.7.0.68)
Requires-Dist: pillow (>=9.1.1)
Requires-Dist: numpy (>=1.24.1)
Requires-Dist: mss (~=7.0.1)
Requires-Dist: imutils (==0.5.4)
